machineid/__init__.py
machineid/py.typed
py_machineid-0.8.1.dist-info/LICENSE
py_machineid-0.8.1.dist-info/METADATA
py_machineid-0.8.1.dist-info/WHEEL
py_machineid-0.8.1.dist-info/top_level.txt
py_machineid-0.8.1.dist-info/RECORD
