Metadata-Version: 2.1
Name: py-machineid
Version: 0.8.1
Summary: Get the unique machine ID of any host (without admin privileges)
Home-page: https://github.com/keygen-sh/py-machineid
Author: Zeke Gabrielse
Author-email: oss@keygen.sh
License: MIT
Platform: UNKNOWN
Classifier: Programming Language :: Python :: 3
Classifier: License :: OSI Approved :: MIT License
Classifier: Operating System :: OS Independent
Requires-Dist: winregistry (<3.0.0,>=2.0.1) ; sys_platform == "win32"
